{"name":{"0":"Neil Wiseman"},"education_text":{"0":"In 1961 after ten years of intermittent contact Wiseman joined the staff of the University Mathematical Laboratory,      University of Cambridge Cambridge, now the      redirect    University of Cambridge Computer Laboratory University of Cambridge Computer Laboratory, as Chief EngineerIn 1970 Wiseman was approved for a PhD through the submission of published work and was appointed to a University LectureshipIn 1970 Wiseman was approved for a PhD through the submission of published work and was appointed to a University Lectureship"},"awards":{"0":0}}